{
    "data": {
        "satellites": [
            {
                "id": "LibreMesh-Sat-001",
                "fingerprint": "H5DL0cbHBpaAHAitNzt7i2oO//wo00/JeK1ARckervs=",
                "hostname": "217.195.184.172",
                "port": 8888,
                "storage_port": 0,
                "mode": "origin",
                "zone": "eu-west",
                "city": "Harbo\u00f8re",
                "coordinates": [
                    56.6175,
                    8.18069
                ]
            },
            {
                "id": "LibreMesh-Storage-001",
                "fingerprint": "CBNpyvDu3uhh0zz8OvN9dqqGFbD08AqjuNE9UWW2Jjw=",
                "hostname": "217.195.184.172",
                "port": 0,
                "storage_port": 12800,
                "mode": "storagenode",
                "zone": "test-local",
                "city": "Harbo\u00f8re",
                "coordinates": [
                    56.6175,
                    8.18069
                ]
            }
        ],
        "repair_nodes": []
    },
    "signature": "JyIrl7F6yuDtI9PbKRQtN7PJeM5dDx5hByPMLw8A9MI/gs7hyrU6167g53ngOnwMQOAs4khIcMLaEU6hUikTzRrdDmT6FwUkpn95GTF8dclaBimR2WqCN0JCot504mejnMXhtHuO42pC0rzkD6jD2f0H1SS2/VUt8rvarqMv2F7HCnjng2TlTbNZfffQuQZO>
}
